pyplexity/__init__.py
pyplexity/__main__.py
pyplexity/dataset_processor/CustomWARCWriter.py
pyplexity/dataset_processor/dataset_processor.py
pyplexity/distributed_files_server.py
pyplexity/perpl_model.py
pyplexity/tag_remover.py
pyplexity-0.2.12.dist-info/LICENSE
pyplexity-0.2.12.dist-info/METADATA
pyplexity-0.2.12.dist-info/WHEEL
pyplexity-0.2.12.dist-info/entry_points.txt
pyplexity-0.2.12.dist-info/RECORD
