Metadata-Version: 2.1
Name: pyplexity
Version: 0.2.12
Summary: Perplexity filter for documents and bulk HTML and WARC boilerplate removal.
Home-page: https://github.com/citiususc/pyplexity
License: GPL-3.0-only
Author: Manuel de Prada Corral
Author-email: manuel.deprada.corral@usc.es
Requires-Python: >=3.6.1,<4.0.0
Classifier: License :: OSI Approved :: GNU General Public License v3 (GPLv3)
Classifier: Programming Language :: Python :: 3
Classifier: Programming Language :: Python :: 3.7
Classifier: Programming Language :: Python :: 3.8
Classifier: Programming Language :: Python :: 3.9
Classifier: Programming Language :: Python :: 3.10
Classifier: Programming Language :: Python :: 3.11
Requires-Dist: Flask (>=2.0.2,<3.0.0)
Requires-Dist: cached-path (>=1.0.2,<2.0.0)
Requires-Dist: html5lib (>=1.1,<2.0)
Requires-Dist: lxml (>=4.7.1,<5.0.0)
Requires-Dist: memory-tempfile (>=2.2.3,<3.0.0)
Requires-Dist: nltk (>=3.6.7,<4.0.0)
Requires-Dist: pandas (>=1.1.5,<2.0.0)
Requires-Dist: storable (>=1.2.4,<2.0.0)
Requires-Dist: typer[all] (>=0.4.0,<0.5.0)
Requires-Dist: warcio (>=1.7.4,<2.0.0)
